datatrails_simplehash/v1.py
datatrails_simplehash/v2.py
datatrails_simplehash-0.5.0.dist-info/LICENSE
datatrails_simplehash-0.5.0.dist-info/METADATA
datatrails_simplehash-0.5.0.dist-info/WHEEL
datatrails_simplehash-0.5.0.dist-info/entry_points.txt
datatrails_simplehash-0.5.0.dist-info/top_level.txt
datatrails_simplehash-0.5.0.dist-info/RECORD
