Metadata-Version: 2.1
Name: datatrails-simplehash
Version: 0.5.0
Summary: DataTrails Simplehash algorithm for DLT Anchoring
Home-page: https://github.com/datatrails/datatrails-simplehash-python
Author: DataTrails Inc.
Author-email: support@datatrails.ai
License: MIT
Project-URL: Source, https://github.com/datatrails/datatrails-simplehash-python
Project-URL: Tracker, https://github.com/datatrails/datatrails-simplehash-python/issues
Classifier: Development Status :: 4 - Beta
Classifier: Environment :: Console
Classifier: Intended Audience :: Developers
Classifier: License :: OSI Approved :: MIT License
Classifier: Operating System :: POSIX :: Linux
Classifier: Programming Language :: Python :: 3.8
Classifier: Topic :: Utilities
Requires-Python: >=3.8
License-File: LICENSE
Requires-Dist: bencode.py ~=4.0
Requires-Dist: requests ~=2.31
